pymultigram/__init__.py
pymultigram/multigram.py
tests/__init__.py
tests/test_pymultigram.py
PyMultigram-0.0.4.dist-info/METADATA
PyMultigram-0.0.4.dist-info/WHEEL
PyMultigram-0.0.4.dist-info/top_level.txt
PyMultigram-0.0.4.dist-info/RECORD
