Metadata-Version: 2.1
Name: PyMultigram
Version: 0.0.4
Summary: Framework for multi-client Pyrogram programs with flexible plugin support.
Home-page: https://github.com/AVee/PyMultigram
Author: AVee
Author-email: pymultigram@avee.org
License: UNKNOWN
Keywords: telegram pyrogram
Platform: UNKNOWN
Classifier: Programming Language :: Python :: 3
Classifier: License :: OSI Approved :: Apache Software License
Classifier: Operating System :: OS Independent
Classifier: Development Status :: 3 - Alpha
Classifier: Intended Audience :: Developers
Requires-Dist: pyrogram (>=0.16)
